youkudownloader
