Metadata-Version: 1.0
Name: youkudownloader
Version: 0.1.5
Summary: Python module and script for downloading video source files from the major video sites in China.
Home-page: http://www.cnblogs.com/feisky/
Author: feisky
Author-email: feiskyer@gmail.com
License: MIT
Keywords: video downloader,youku
Platform: Independant
